whatsplay/__init__.py
whatsplay/base_client.py
whatsplay/chat_manager.py
whatsplay/client.py
whatsplay/event.py
whatsplay/state_manager.py
whatsplay/utils.py
whatsplay/wa_elements.py
whatsplay/auth/__init__.py
whatsplay/auth/auth.py
whatsplay/auth/local_profile_auth.py
whatsplay/auth/no_auth.py
whatsplay/constants/locator.py
whatsplay/constants/states.py
whatsplay/events/__init__.py
whatsplay/events/event_handler.py
whatsplay/events/event_types.py
whatsplay/filters/__init__.py
whatsplay/filters/filters.py
whatsplay/filters/message_filter.py
whatsplay/object/message.py
whatsplay-1.9.7.dist-info/licenses/LICENSE
whatsplay-1.9.7.dist-info/METADATA
whatsplay-1.9.7.dist-info/WHEEL
whatsplay-1.9.7.dist-info/top_level.txt
whatsplay-1.9.7.dist-info/RECORD
