Metadata-Version: 2.4
Name: whatsplay
Version: 1.9.7
Summary: A modern Python library for automating WhatsApp Web using Playwright
Author-email: Marcos Bustos <markbustos1912@gmail.com>
License: MIT
Project-URL: Homepage, https://github.com/markbus-ai/whatsplay
Project-URL: Documentation, https://github.com/markbus-ai/whatsplay#readme
Project-URL: Issues, https://github.com/markbus-ai/whatsplay/issues
Keywords: whatsapp,automation,playwright,bot
Classifier: Development Status :: 4 - Beta
Classifier: Intended Audience :: Developers
Classifier: License :: OSI Approved :: MIT License
Classifier: Programming Language :: Python :: 3
Classifier: Programming Language :: Python :: 3.8
Classifier: Programming Language :: Python :: 3.9
Classifier: Programming Language :: Python :: 3.10
Classifier: Programming Language :: Python :: 3.11
Classifier: Topic :: Software Development :: Libraries :: Python Modules
Classifier: Topic :: Communications :: Chat
Requires-Python: >=3.8
License-File: LICENSE
Requires-Dist: playwright>=1.35.0
Requires-Dist: opencv-python>=4.8.0
Requires-Dist: numpy>=1.24.0
Dynamic: license-file
